ami_nika2
setup.cfg
setup.py
pyAMI_nika2/__init__.py
pyAMI_nika2/config.py
pyAMI_nika2.egg-info/PKG-INFO
pyAMI_nika2.egg-info/SOURCES.txt
pyAMI_nika2.egg-info/dependency_links.txt
pyAMI_nika2.egg-info/not-zip-safe
pyAMI_nika2.egg-info/requires.txt
pyAMI_nika2.egg-info/top_level.txt