Metadata-Version: 1.0
Name: pyAMI-nika2
Version: 1.0.2
Summary: Python AMI Metadata Interface (pyAMI) for NIKA 2
Home-page: http://ami.in2p3.fr/
Author: Jerome Odier, Fabian Lambert
Author-email: jerome.odier@cern.ch, fabian.lambert@lpsc.in2p3.fr
License: CeCILL-C
Platform: any
